sklearn_raster/__init__.py
sklearn_raster/estimator.py
sklearn_raster/features.py
sklearn_raster/types.py
sklearn_raster/ufunc.py
sklearn_raster/datasets/__init__.py
sklearn_raster/datasets/_base.py
sklearn_raster/datasets/_registry.py
sklearn_raster/datasets/synthetic.py
sklearn_raster/utils/__init__.py
sklearn_raster/utils/decorators.py
sklearn_raster/utils/estimator.py
sklearn_raster/utils/features.py
sklearn_raster-0.1.0.dev2.dist-info/METADATA
sklearn_raster-0.1.0.dev2.dist-info/WHEEL
sklearn_raster-0.1.0.dev2.dist-info/RECORD
