Metadata-Version: 2.4
Name: sklearn-raster
Version: 0.1.0.dev2
Summary: Spatial raster prediction with scikit-learn estimators.
Project-URL: Homepage, https://github.com/lemma-osu/sklearn-raster
Author-email: Aaron Zuspan <aaron.zuspan@oregonstate.edu>, Matt Gregory <matt.gregory@oregonstate.edu>
Requires-Python: >=3.9
Requires-Dist: dask
Requires-Dist: numpy
Requires-Dist: scikit-learn
Requires-Dist: typing-extensions
Requires-Dist: xarray
Provides-Extra: datasets
Requires-Dist: pooch; extra == 'datasets'
Requires-Dist: rasterio; extra == 'datasets'
Requires-Dist: rioxarray; extra == 'datasets'
Requires-Dist: sknnr; extra == 'datasets'
Provides-Extra: tutorials
Requires-Dist: ipykernel; extra == 'tutorials'
Requires-Dist: matplotlib; extra == 'tutorials'
Requires-Dist: pooch; extra == 'tutorials'
Requires-Dist: rasterio; extra == 'tutorials'
Requires-Dist: rioxarray; extra == 'tutorials'
Requires-Dist: sknnr; extra == 'tutorials'
